deteefapi/__init__.py
deteefapi/dtf.py
deteefapi/entry.py
deteefapi/objects.py
deteefapi/webhook.py
deteefapi/test/__init__.py
deteefapi/test/test_basic.py
deteefapi/test/test_check_data.py
deteefapi/test/test_massive.py
deteefapi/test/test_media.py
deteefapi/test/test_tools.py
deteefapi/test/test_webhook.py
deteefapi-0.4.2.dist-info/METADATA
deteefapi-0.4.2.dist-info/WHEEL
deteefapi-0.4.2.dist-info/top_level.txt
deteefapi-0.4.2.dist-info/RECORD
