Metadata-Version: 2.1
Name: deteefapi
Version: 0.4.2
Summary: API for daily telegraf
Home-page: UNKNOWN
Author: Smyek
Author-email: smyek.job@gmail.com
License: MIT
Platform: UNKNOWN
Requires-Dist: requests
Requires-Dist: ratelimit
